configmgr.py
setup.py
configmgr.egg-info/PKG-INFO
configmgr.egg-info/SOURCES.txt
configmgr.egg-info/dependency_links.txt
configmgr.egg-info/requires.txt
configmgr.egg-info/top_level.txt