Metadata-Version: 1.0
Name: configmgr
Version: 0.0
Summary: simple configuration management
Home-page: https://bitbucket.org/grantor61/configmgr
Author: grantor61
Author-email: grantor61@gmail.com
License: MIT license
Platform: linux
Platform: win32
Classifier: Development Status :: 4 - Beta
Classifier: Intended Audience :: Developers
Classifier: License :: OSI Approved :: MIT License
Classifier: Operating System :: POSIX
Classifier: Operating System :: Microsoft :: Windows
Classifier: Topic :: Software Development :: Libraries
Classifier: Topic :: Utilities
Classifier: Programming Language :: Python
